DESCRIPTION
HISTORY.rst
MANIFEST.in
README.rst
VERSION
conftest.py
findpackages.py
requirements.txt
setup.py
Flask_JqueryUiBootstrap.egg-info/PKG-INFO
Flask_JqueryUiBootstrap.egg-info/SOURCES.txt
Flask_JqueryUiBootstrap.egg-info/dependency_links.txt
Flask_JqueryUiBootstrap.egg-info/not-zip-safe
Flask_JqueryUiBootstrap.egg-info/requires.txt
Flask_JqueryUiBootstrap.egg-info/top_level.txt
SAMPLE_PROJECT/__init__.py
SAMPLE_PROJECT/wtf-app.py
SAMPLE_PROJECT/wtf-less-app.py
docs/development.rst
flask_jqueryuibootstrap/__init__.py
flask_jqueryuibootstrap/static/assets/css/bootstrap.min.css
flask_jqueryuibootstrap/static/assets/css/font-awesome-ie7.min.css
flask_jqueryuibootstrap/static/assets/css/font-awesome.min.css
flask_jqueryuibootstrap/static/assets/css/font/FontAwesome.otf
flask_jqueryuibootstrap/static/assets/css/font/fontawesome-webfont.eot
flask_jqueryuibootstrap/static/assets/css/font/fontawesome-webfont.svg
flask_jqueryuibootstrap/static/assets/css/font/fontawesome-webfont.ttf
flask_jqueryuibootstrap/static/assets/css/font/fontawesome-webfont.woff
flask_jqueryuibootstrap/static/assets/ico/apple-touch-icon-114-precomposed.png
flask_jqueryuibootstrap/static/assets/ico/apple-touch-icon-144-precomposed.png
flask_jqueryuibootstrap/static/assets/ico/apple-touch-icon-57-precomposed.png
flask_jqueryuibootstrap/static/assets/ico/apple-touch-icon-72-precomposed.png
flask_jqueryuibootstrap/static/assets/ico/favicon.ico
flask_jqueryuibootstrap/static/assets/ico/favicon.png
flask_jqueryuibootstrap/static/assets/img/bs-docs-masthead-pattern.png
flask_jqueryuibootstrap/static/assets/js/bootstrap.min.js
flask_jqueryuibootstrap/static/assets/js/jquery-1.9.0.min.js
flask_jqueryuibootstrap/static/assets/js/jquery-ui-1.10.0.custom.min.js
flask_jqueryuibootstrap/static/css/jquery-ui-1.10.0.custom.css
flask_jqueryuibootstrap/static/css/jquery-ui-1.9.2.custom.css
flask_jqueryuibootstrap/static/css/jquery.ui.1.10.0.ie.css
flask_jqueryuibootstrap/static/css/jquery.ui.1.9.2.ie.css
flask_jqueryuibootstrap/static/css/images/ui-bg_flat_0_aaaaaa_40x100.png
flask_jqueryuibootstrap/static/css/images/ui-bg_glass_55_fbf9ee_1x400.png
flask_jqueryuibootstrap/static/css/images/ui-bg_glass_65_ffffff_1x400.png
