Metadata-Version: 1.1
Name: Flask-JqueryUiBootstrap
Version: 0.5.0.4
Summary: Flask jQuery UI Bootstrap minimalistic fork of Flask-Bootsrap extension
Home-page: https://github.com/lightningwolf/Flask-JqueryUiBootstrap
Author: Arkadiusz Tułodziecki
Author-email: atulodzi@gmail.com
License: MIT
Platform: any
Classifier: Development Status :: 3 - Alpha
Classifier: Environment :: Web Environment
Classifier: Intended Audience :: Developers
Classifier: Natural Language :: Polish
Classifier: License :: OSI Approved :: MIT License
Classifier: Operating System :: OS Independent
Classifier: Programming Language :: Python
Classifier: Topic :: Internet :: WWW/HTTP :: Dynamic Content
Classifier: Topic :: Software Development :: Libraries :: Python Modules
